search_lyrics/__init__.py
search_lyrics/__main__.py
search_lyrics/__version__.py
search_lyrics/entrypoint.py
search_lyrics/exceptions.py
search_lyrics/main.py
search_lyrics-0.0.2.dist-info/entry_points.txt
search_lyrics-0.0.2.dist-info/WHEEL
search_lyrics-0.0.2.dist-info/METADATA
search_lyrics-0.0.2.dist-info/licenses/LICENSE
search_lyrics-0.0.2.dist-info/RECORD
